verselect/__init__.py
verselect/apps.py
verselect/docs/__init__.py
verselect/docs/docs.html
verselect/exceptions.py
verselect/middleware.py
verselect/py.typed
verselect/routing.py
verselect/utils.py
verselect_zmievsa-0.0.6.dist-info/LICENSE
verselect_zmievsa-0.0.6.dist-info/WHEEL
verselect_zmievsa-0.0.6.dist-info/METADATA
verselect_zmievsa-0.0.6.dist-info/RECORD
